{
  "font-family-default": {
    "value": "{font-family-sans-serif}"
  },
  "font-family-sans-serif": {
    "value": "Adobe Clean"
  },
  "font-family-serif": {
    "value": "Adobe Clean Serif"
  },
  "font-family-code": {
    "value": "Source Code Pro"
  },
  "font-family-cjk": {
    "value": "Adobe Clean Han"
  },
  "font-weight-light": {
    "value": "light"
  },
  "font-weight-regular": {
    "value": "regular"
  },
  "font-weight-medium": {
    "value": "medium"
  },
  "font-weight-bold": {
    "value": "bold"
  },
  "font-weight-extra-bold": {
    "value": "extra-bold"
  },
  "font-weight-black": {
    "value": "black"
  },
  "font-style-italic": {
    "value": "italic"
  },
  "font-style-default": {
    "value": "normal"
  },
  "font-size-50": {
    "sets": {
      "desktop": {
        "value": "11px"
      },
      "mobile": {
        "value": "13px"
      }
    }
  },
  "font-size-75": {
    "sets": {
      "desktop": {
        "value": "12px"
      },
      "mobile": {
        "value": "15px"
      }
    }
  },
  "font-size-100": {
    "sets": {
      "desktop": {
        "value": "14px"
      },
      "mobile": {
        "value": "17px"
      }
    }
  },
  "font-size-200": {
    "sets": {
      "desktop": {
        "value": "16px"
      },
      "mobile": {
        "value": "19px"
      }
    }
  },
  "font-size-300": {
    "sets": {
      "desktop": {
        "value": "18px"
      },
      "mobile": {
        "value": "22px"
      }
    }
  },
  "font-size-400": {
    "sets": {
      "desktop": {
        "value": "20px"
      },
      "mobile": {
        "value": "24px"
      }
    }
  },
  "font-size-500": {
    "sets": {
      "desktop": {
        "value": "22px"
      },
      "mobile": {
        "value": "27px"
      }
    }
  },
  "font-size-600": {
    "sets": {
      "desktop": {
        "value": "25px"
      },
      "mobile": {
        "value": "31px"
      }
    }
  },
  "font-size-700": {
    "sets": {
      "desktop": {
        "value": "28px"
      },
      "mobile": {
        "value": "34px"
      }
    }
  },
  "font-size-800": {
    "sets": {
      "desktop": {
        "value": "32px"
      },
      "mobile": {
        "value": "39px"
      }
    }
  },
  "font-size-900": {
    "sets": {
      "desktop": {
        "value": "36px"
      },
      "mobile": {
        "value": "44px"
      }
    }
  },
  "font-size-1000": {
    "sets": {
      "desktop": {
        "value": "40px"
      },
      "mobile": {
        "value": "49px"
      }
    }
  },
  "font-size-1100": {
    "sets": {
      "desktop": {
        "value": "45px"
      },
      "mobile": {
        "value": "55px"
      }
    }
  },
  "font-size-1200": {
    "sets": {
      "desktop": {
        "value": "50px"
      },
      "mobile": {
        "value": "62px"
      }
    }
  },
  "font-size-1300": {
    "sets": {
      "desktop": {
        "value": "60px"
      },
      "mobile": {
        "value": "70px"
      }
    }
  },
  "line-height-100": {
    "value": "1.3"
  },
  "line-height-200": {
    "value": "1.5"
  },
  "line-height-cjk-100": {
    "value": "1.5"
  },
  "line-height-cjk-200": {
    "value": "1.7"
  },
  "letter-spacing-cjk": {
    "value": "0.05em"
  },
  "heading-sans-serif-font-family": {
    "value": "{font-family-sans-serif}",
    "component": "heading"
  },
  "heading-serif-font-family": {
    "value": "{font-family-serif}",
    "component": "heading"
  },
  "heading-cjk-font-family": {
    "value": "{font-family-cjk}",
    "component": "heading"
  },
  "heading-sans-serif-light-font-weight": {
    "value": "{font-weight-light}",
    "component": "heading"
  },
  "heading-sans-serif-light-font-style": {
    "value": "{font-style-default}",
    "component": "heading"
  },
  "heading-serif-light-font-weight": {
    "value": "{font-weight-regular}",
    "component": "heading"
  },
  "heading-serif-light-font-style": {
    "value": "{font-style-default}",
    "component": "heading"
  },
  "heading-cjk-light-font-weight": {
    "value": "{font-weight-light}",
    "component": "heading"
  },
  "heading-cjk-light-font-style": {
    "value": "{font-style-default}",
    "component": "heading"
  },
  "heading-sans-serif-font-weight": {
    "sets": {
      "spectrum": {
        "value": "{font-weight-bold}"
      },
      "express": {
        "value": "{font-weight-black}"
      }
    },
    "component": "heading"
  },
  "heading-sans-serif-font-style": {
    "value": "{font-style-default}",
    "component": "heading"
  },
  "heading-serif-font-weight": {
    "sets": {
      "spectrum": {
        "value": "{font-weight-bold}"
      },
      "express": {
        "value": "{font-weight-black}"
      }
    },
    "component": "heading"
  },
  "heading-serif-font-style": {
    "value": "{font-style-default}",
    "component": "heading"
  },
  "heading-cjk-font-weight": {
    "sets": {
      "spectrum": {
        "value": "{font-weight-extra-bold}"
      },
      "express": {
        "value": "{font-weight-black}"
      }
    },
    "component": "heading"
  },
  "heading-cjk-font-style": {
    "value": "{font-style-default}",
    "component": "heading"
  },
  "heading-sans-serif-heavy-font-weight": {
    "value": "{font-weight-black}",
    "component": "heading"
  },
  "heading-sans-serif-heavy-font-style": {
    "value": "{font-style-default}",
    "component": "heading"
  },
  "heading-serif-heavy-font-weight": {
    "value": "{font-weight-black}",
    "component": "heading"
  },
  "heading-serif-heavy-font-style": {
    "value": "{font-style-default}",
    "component": "heading"
  },
  "heading-cjk-heavy-font-weight": {
    "value": "{font-weight-black}",
    "component": "heading"
  },
  "heading-cjk-heavy-font-style": {
    "value": "{font-style-default}",
    "component": "heading"
  },
  "heading-sans-serif-light-strong-font-weight": {
    "value": "{font-weight-bold}",
    "component": "heading"
  },
  "heading-sans-serif-light-strong-font-style": {
    "value": "{font-style-default}",
    "component": "heading"
  },
  "heading-serif-light-strong-font-weight": {
    "value": "{font-weight-bold}",
    "component": "heading"
  },
  "heading-serif-light-strong-font-style": {
    "value": "{font-style-default}",
    "component": "heading"
  },
  "heading-cjk-light-strong-font-weight": {
    "value": "{font-weight-extra-bold}",
    "component": "heading"
  },
  "heading-cjk-light-strong-font-style": {
    "value": "{font-style-default}",
    "component": "heading"
  },
  "heading-sans-serif-strong-font-weight": {
    "value": "{font-weight-black}",
    "component": "heading"
  },
  "heading-sans-serif-strong-font-style": {
    "value": "{font-style-default}",
    "component": "heading"
  },
  "heading-serif-strong-font-weight": {
    "value": "{font-weight-black}",
    "component": "heading"
  },
  "heading-serif-strong-font-style": {
    "value": "{font-style-default}",
    "component": "heading"
  },
  "heading-cjk-strong-font-weight": {
    "value": "{font-weight-black}",
    "component": "heading"
  },
  "heading-cjk-strong-font-style": {
    "value": "{font-style-default}",
    "component": "heading"
  },
  "heading-sans-serif-heavy-strong-font-weight": {
    "value": "{font-weight-black}",
    "component": "heading"
  },
  "heading-sans-serif-heavy-strong-font-style": {
    "value": "{font-style-default}",
    "component": "heading"
  },
  "heading-serif-heavy-strong-font-weight": {
    "value": "{font-weight-black}",
    "component": "heading"
  },
  "heading-serif-heavy-strong-font-style": {
    "value": "{font-style-default}",
    "component": "heading"
  },
  "heading-cjk-heavy-strong-font-weight": {
    "value": "{font-weight-black}",
    "component": "heading"
  },
  "heading-cjk-heavy-strong-font-style": {
    "value": "{font-style-default}",
    "component": "heading"
  },
  "heading-sans-serif-light-emphasized-font-weight": {
    "value": "{font-weight-light}",
    "component": "heading"
  },
  "heading-sans-serif-light-emphasized-font-style": {
    "value": "{font-style-italic}",
    "component": "heading"
  },
  "heading-serif-light-emphasized-font-weight": {
    "value": "{font-weight-regular}",
    "component": "heading"
  },
  "heading-serif-light-emphasized-font-style": {
    "value": "{font-style-italic}",
    "component": "heading"
  },
  "heading-cjk-light-emphasized-font-weight": {
    "value": "{font-weight-regular}",
    "component": "heading"
  },
  "heading-cjk-light-emphasized-font-style": {
    "value": "{font-style-default}",
    "component": "heading"
  },
  "heading-sans-serif-emphasized-font-weight": {
    "sets": {
      "spectrum": {
        "value": "{font-weight-bold}"
      },
      "express": {
        "value": "{font-weight-black}"
      }
    },
    "component": "heading"
  },
  "heading-sans-serif-emphasized-font-style": {
    "value": "{font-style-italic}",
    "component": "heading"
  },
  "heading-serif-emphasized-font-weight": {
    "sets": {
      "spectrum": {
        "value": "{font-weight-bold}"
      },
      "express": {
        "value": "{font-weight-black}"
      }
    },
    "component": "heading"
  },
  "heading-serif-emphasized-font-style": {
    "value": "{font-style-italic}",
    "component": "heading"
  },
  "heading-cjk-emphasized-font-weight": {
    "value": "{font-weight-black}",
    "component": "heading"
  },
  "heading-cjk-emphasized-font-style": {
    "value": "{font-style-default}",
    "component": "heading"
  },
  "heading-sans-serif-heavy-emphasized-font-weight": {
    "value": "{font-weight-black}",
    "component": "heading"
  },
  "heading-sans-serif-heavy-emphasized-font-style": {
    "value": "{font-style-italic}",
    "component": "heading"
  },
  "heading-serif-heavy-emphasized-font-weight": {
    "value": "{font-weight-black}",
    "component": "heading"
  },
  "heading-serif-heavy-emphasized-font-style": {
    "value": "{font-style-italic}",
    "component": "heading"
  },
  "heading-cjk-heavy-emphasized-font-weight": {
    "value": "{font-weight-black}",
    "component": "heading"
  },
  "heading-cjk-heavy-emphasized-font-style": {
    "value": "{font-style-default}",
    "component": "heading"
  },
  "heading-sans-serif-light-strong-emphasized-font-weight": {
    "value": "{font-weight-bold}",
    "component": "heading"
  },
  "heading-sans-serif-light-strong-emphasized-font-style": {
    "value": "{font-style-italic}",
    "component": "heading"
  },
  "heading-serif-light-strong-emphasized-font-weight": {
    "value": "{font-weight-bold}",
    "component": "heading"
  },
  "heading-serif-light-strong-emphasized-font-style": {
    "value": "{font-style-italic}",
    "component": "heading"
  },
  "heading-cjk-light-strong-emphasized-font-weight": {
    "value": "{font-weight-extra-bold}",
    "component": "heading"
  },
  "heading-cjk-light-strong-emphasized-font-style": {
    "value": "{font-style-default}",
    "component": "heading"
  },
  "heading-sans-serif-strong-emphasized-font-weight": {
    "value": "{font-weight-black}",
    "component": "heading"
  },
  "heading-sans-serif-strong-emphasized-font-style": {
    "value": "{font-style-italic}",
    "component": "heading"
  },
  "heading-serif-strong-emphasized-font-weight": {
    "value": "{font-weight-black}",
    "component": "heading"
  },
  "heading-serif-strong-emphasized-font-style": {
    "value": "{font-style-italic}",
    "component": "heading"
  },
  "heading-cjk-strong-emphasized-font-weight": {
    "value": "{font-weight-black}",
    "component": "heading"
  },
  "heading-cjk-strong-emphasized-font-style": {
    "value": "{font-style-default}",
    "component": "heading"
  },
  "heading-sans-serif-heavy-strong-emphasized-font-weight": {
    "value": "{font-weight-black}",
    "component": "heading"
  },
  "heading-sans-serif-heavy-strong-emphasized-font-style": {
    "value": "{font-style-italic}",
    "component": "heading"
  },
  "heading-serif-heavy-strong-emphasized-font-weight": {
    "value": "{font-weight-black}",
    "component": "heading"
  },
  "heading-serif-heavy-strong-emphasized-font-style": {
    "value": "{font-style-italic}",
    "component": "heading"
  },
  "heading-cjk-heavy-strong-emphasized-font-weight": {
    "value": "{font-weight-black}",
    "component": "heading"
  },
  "heading-cjk-heavy-strong-emphasized-font-style": {
    "value": "{font-style-default}",
    "component": "heading"
  },
  "heading-size-xxxl": {
    "value": "{font-size-1300}",
    "component": "heading"
  },
  "heading-size-xxl": {
    "value": "{font-size-1100}",
    "component": "heading"
  },
  "heading-size-xl": {
    "value": "{font-size-900}",
    "component": "heading"
  },
  "heading-size-l": {
    "value": "{font-size-700}",
    "component": "heading"
  },
  "heading-size-m": {
    "value": "{font-size-500}",
    "component": "heading"
  },
  "heading-size-s": {
    "value": "{font-size-300}",
    "component": "heading"
  },
  "heading-size-xs": {
    "value": "{font-size-200}",
    "component": "heading"
  },
  "heading-size-xxs": {
    "value": "{font-size-100}",
    "component": "heading"
  },
  "heading-line-height": {
    "value": "{line-height-100}",
    "component": "heading"
  },
  "heading-line-height-cjk": {
    "value": "{line-height-cjk-100}",
    "component": "heading"
  },
  "heading-margin-top-multiplier": {
    "value": "0.88888889",
    "component": "heading"
  },
  "heading-margin-bottom-multiplier": {
    "value": "0.25",
    "component": "heading"
  },
  "body-sans-serif-font-family": {
    "value": "{font-family-sans-serif}",
    "component": "body"
  },
  "body-serif-font-family": {
    "value": "{font-family-serif}",
    "component": "body"
  },
  "body-cjk-font-family": {
    "value": "{font-family-cjk}",
    "component": "body"
  },
  "body-sans-serif-font-weight": {
    "value": "{font-weight-regular}",
    "component": "body"
  },
  "body-sans-serif-font-style": {
    "value": "{font-style-default}",
    "component": "body"
  },
  "body-serif-font-weight": {
    "value": "{font-weight-regular}",
    "component": "body"
  },
  "body-serif-font-style": {
    "value": "{font-style-default}",
    "component": "body"
  },
  "body-cjk-font-weight": {
    "value": "{font-weight-regular}",
    "component": "body"
  },
  "body-cjk-font-style": {
    "value": "{font-style-default}",
    "component": "body"
  },
  "body-sans-serif-strong-font-weight": {
    "value": "{font-weight-bold}",
    "component": "body"
  },
  "body-sans-serif-strong-font-style": {
    "value": "{font-style-default}",
    "component": "body"
  },
  "body-serif-strong-font-weight": {
    "value": "{font-weight-bold}",
    "component": "body"
  },
  "body-serif-strong-font-style": {
    "value": "{font-style-default}",
    "component": "body"
  },
  "body-cjk-strong-font-weight": {
    "value": "{font-weight-black}",
    "component": "body"
  },
  "body-cjk-strong-font-style": {
    "value": "{font-style-default}",
    "component": "body"
  },
  "body-sans-serif-emphasized-font-weight": {
    "value": "{font-weight-regular}",
    "component": "body"
  },
  "body-sans-serif-emphasized-font-style": {
    "value": "{font-style-italic}",
    "component": "body"
  },
  "body-serif-emphasized-font-weight": {
    "value": "{font-weight-regular}",
    "component": "body"
  },
  "body-serif-emphasized-font-style": {
    "value": "{font-style-italic}",
    "component": "body"
  },
  "body-cjk-emphasized-font-weight": {
    "value": "{font-weight-extra-bold}",
    "component": "body"
  },
  "body-cjk-emphasized-font-style": {
    "value": "{font-style-default}",
    "component": "body"
  },
  "body-sans-serif-strong-emphasized-font-weight": {
    "value": "{font-weight-bold}",
    "component": "body"
  },
  "body-sans-serif-strong-emphasized-font-style": {
    "value": "{font-style-italic}",
    "component": "body"
  },
  "body-serif-strong-emphasized-font-weight": {
    "value": "{font-weight-bold}",
    "component": "body"
  },
  "body-serif-strong-emphasized-font-style": {
    "value": "{font-style-italic}",
    "component": "body"
  },
  "body-cjk-strong-emphasized-font-weight": {
    "value": "{font-weight-black}",
    "component": "body"
  },
  "body-cjk-strong-emphasized-font-style": {
    "value": "{font-style-default}",
    "component": "body"
  },
  "body-size-xxxl": {
    "value": "{font-size-600}",
    "component": "body"
  },
  "body-size-xxl": {
    "value": "{font-size-500}",
    "component": "body"
  },
  "body-size-xl": {
    "value": "{font-size-400}",
    "component": "body"
  },
  "body-size-l": {
    "value": "{font-size-300}",
    "component": "body"
  },
  "body-size-m": {
    "value": "{font-size-200}",
    "component": "body"
  },
  "body-size-s": {
    "value": "{font-size-100}",
    "component": "body"
  },
  "body-size-xs": {
    "value": "{font-size-75}",
    "component": "body"
  },
  "body-line-height": {
    "value": "{line-height-200}",
    "component": "body"
  },
  "body-line-height-cjk": {
    "value": "{line-height-cjk-200}",
    "component": "body"
  },
  "body-margin-multiplier": {
    "value": "0.75",
    "component": "body"
  },
  "detail-sans-serif-font-family": {
    "value": "{font-family-sans-serif}",
    "component": "detail"
  },
  "detail-sans-serif-font-weight": {
    "value": "{font-weight-bold}",
    "component": "detail"
  },
  "detail-sans-serif-font-style": {
    "value": "{font-style-default}",
    "component": "detail"
  },
  "detail-serif-font-family": {
    "value": "{font-family-serif}",
    "component": "detail"
  },
  "detail-serif-font-weight": {
    "value": "{font-weight-bold}",
    "component": "detail"
  },
  "detail-serif-font-style": {
    "value": "{font-style-default}",
    "component": "detail"
  },
  "detail-cjk-font-family": {
    "value": "{font-family-cjk}",
    "component": "detail"
  },
  "detail-cjk-font-weight": {
    "value": "{font-weight-extra-bold}",
    "component": "detail"
  },
  "detail-cjk-font-style": {
    "value": "{font-style-default}",
    "component": "detail"
  },
  "detail-sans-serif-light-font-weight": {
    "value": "{font-weight-regular}",
    "component": "detail"
  },
  "detail-sans-serif-light-font-style": {
    "value": "{font-style-default}",
    "component": "detail"
  },
  "detail-serif-light-font-weight": {
    "value": "{font-weight-regular}",
    "component": "detail"
  },
  "detail-serif-light-font-style": {
    "value": "{font-style-default}",
    "component": "detail"
  },
  "detail-cjk-light-font-weight": {
    "value": "{font-weight-light}",
    "component": "detail"
  },
  "detail-cjk-light-font-style": {
    "value": "{font-style-default}",
    "component": "detail"
  },
  "detail-sans-serif-strong-font-weight": {
    "value": "{font-weight-bold}",
    "component": "detail"
  },
  "detail-sans-serif-strong-font-style": {
    "value": "{font-style-default}",
    "component": "detail"
  },
  "detail-serif-strong-font-weight": {
    "value": "{font-weight-bold}",
    "component": "detail"
  },
  "detail-serif-strong-font-style": {
    "value": "{font-style-default}",
    "component": "detail"
  },
  "detail-cjk-strong-font-weight": {
    "value": "{font-weight-black}",
    "component": "detail"
  },
  "detail-cjk-strong-font-style": {
    "value": "{font-style-default}",
    "component": "detail"
  },
  "detail-sans-serif-light-strong-font-weight": {
    "value": "{font-weight-regular}",
    "component": "detail"
  },
  "detail-sans-serif-light-strong-font-style": {
    "value": "{font-style-default}",
    "component": "detail"
  },
  "detail-serif-light-strong-font-weight": {
    "value": "{font-weight-regular}",
    "component": "detail"
  },
  "detail-serif-light-strong-font-style": {
    "value": "{font-style-default}",
    "component": "detail"
  },
  "detail-cjk-light-strong-font-weight": {
    "value": "{font-weight-extra-bold}",
    "component": "detail"
  },
  "detail-cjk-light-strong-font-style": {
    "value": "{font-style-default}",
    "component": "detail"
  },
  "detail-sans-serif-emphasized-font-weight": {
    "value": "{font-weight-bold}",
    "component": "detail"
  },
  "detail-sans-serif-emphasized-font-style": {
    "value": "{font-style-italic}",
    "component": "detail"
  },
  "detail-serif-emphasized-font-weight": {
    "value": "{font-weight-bold}",
    "component": "detail"
  },
  "detail-serif-emphasized-font-style": {
    "value": "{font-style-italic}",
    "component": "detail"
  },
  "detail-cjk-emphasized-font-weight": {
    "value": "{font-weight-black}",
    "component": "detail"
  },
  "detail-cjk-emphasized-font-style": {
    "value": "{font-style-default}",
    "component": "detail"
  },
  "detail-sans-serif-light-emphasized-font-weight": {
    "value": "{font-weight-regular}",
    "component": "detail"
  },
  "detail-sans-serif-light-emphasized-font-style": {
    "value": "{font-style-italic}",
    "component": "detail"
  },
  "detail-serif-light-emphasized-font-weight": {
    "value": "{font-weight-regular}",
    "component": "detail"
  },
  "detail-serif-light-emphasized-font-style": {
    "value": "{font-style-italic}",
    "component": "detail"
  },
  "detail-cjk-light-emphasized-font-weight": {
    "value": "{font-weight-regular}",
    "component": "detail"
  },
  "detail-cjk-light-emphasized-font-style": {
    "value": "{font-style-default}",
    "component": "detail"
  },
  "detail-sans-serif-strong-emphasized-font-weight": {
    "value": "{font-weight-bold}",
    "component": "detail"
  },
  "detail-sans-serif-strong-emphasized-font-style": {
    "value": "{font-style-italic}",
    "component": "detail"
  },
  "detail-serif-strong-emphasized-font-weight": {
    "value": "{font-weight-bold}",
    "component": "detail"
  },
  "detail-serif-strong-emphasized-font-style": {
    "value": "{font-style-italic}",
    "component": "detail"
  },
  "detail-cjk-strong-emphasized-font-weight": {
    "value": "{font-weight-black}",
    "component": "detail"
  },
  "detail-cjk-strong-emphasized-font-style": {
    "value": "{font-style-default}",
    "component": "detail"
  },
  "detail-sans-serif-light-strong-emphasized-font-weight": {
    "value": "{font-weight-regular}",
    "component": "detail"
  },
  "detail-sans-serif-light-strong-emphasized-font-style": {
    "value": "{font-style-italic}",
    "component": "detail"
  },
  "detail-serif-light-strong-emphasized-font-weight": {
    "value": "{font-weight-regular}",
    "component": "detail"
  },
  "detail-serif-light-strong-emphasized-font-style": {
    "value": "{font-style-italic}",
    "component": "detail"
  },
  "detail-cjk-light-strong-emphasized-font-weight": {
    "value": "{font-weight-extra-bold}",
    "component": "detail"
  },
  "detail-cjk-light-strong-emphasized-font-style": {
    "value": "{font-style-default}",
    "component": "detail"
  },
  "detail-size-xl": {
    "value": "{font-size-200}",
    "component": "detail"
  },
  "detail-size-l": {
    "value": "{font-size-100}",
    "component": "detail"
  },
  "detail-size-m": {
    "value": "{font-size-75}",
    "component": "detail"
  },
  "detail-size-s": {
    "value": "{font-size-50}",
    "component": "detail"
  },
  "detail-line-height": {
    "value": "{line-height-100}",
    "component": "detail"
  },
  "detail-line-height-cjk": {
    "value": "{line-height-cjk-100}",
    "component": "detail"
  },
  "detail-margin-top-mulitplier": {
    "value": "0.88888889",
    "component": "detail"
  },
  "detail-margin-bottom-multiplier": {
    "value": "0.25",
    "component": "detail"
  },
  "detail-letter-spacing": {
    "value": "0.06em",
    "component": "detail"
  },
  "code-font-family": {
    "value": "{font-family-code}",
    "component": "code"
  },
  "code-font-weight": {
    "value": "{font-weight-regular}",
    "component": "code"
  },
  "code-font-style": {
    "value": "{font-style-default}",
    "component": "code"
  },
  "code-cjk-font-family": {
    "value": "{font-family-code}",
    "component": "code"
  },
  "code-cjk-font-weight": {
    "value": "{font-weight-regular}",
    "component": "code"
  },
  "code-cjk-font-style": {
    "value": "{font-style-default}",
    "component": "code"
  },
  "code-strong-font-weight": {
    "value": "{font-weight-bold}",
    "component": "code"
  },
  "code-strong-font-style": {
    "value": "{font-style-default}",
    "component": "code"
  },
  "code-cjk-strong-font-weight": {
    "value": "{font-weight-black}",
    "component": "code"
  },
  "code-cjk-strong-font-style": {
    "value": "{font-style-default}",
    "component": "code"
  },
  "code-emphasized-font-weight": {
    "value": "{font-weight-regular}",
    "component": "code"
  },
  "code-emphasized-font-style": {
    "value": "{font-style-italic}",
    "component": "code"
  },
  "code-cjk-emphasized-font-weight": {
    "value": "{font-weight-bold}",
    "component": "code"
  },
  "code-cjk-emphasized-font-style": {
    "value": "{font-style-default}",
    "component": "code"
  },
  "code-strong-emphasized-font-weight": {
    "value": "{font-weight-bold}",
    "component": "code"
  },
  "code-strong-emphasized-font-style": {
    "value": "{font-style-italic}",
    "component": "code"
  },
  "code-cjk-strong-emphasized-font-weight": {
    "value": "{font-weight-black}",
    "component": "code"
  },
  "code-cjk-strong-emphasized-font-style": {
    "value": "{font-style-default}",
    "component": "code"
  },
  "code-size-xl": {
    "value": "{font-size-400}",
    "component": "code"
  },
  "code-size-l": {
    "value": "{font-size-300}",
    "component": "code"
  },
  "code-size-m": {
    "value": "{font-size-200}",
    "component": "code"
  },
  "code-size-s": {
    "value": "{font-size-100}",
    "component": "code"
  },
  "code-size-xs": {
    "value": "{font-size-75}",
    "component": "code"
  },
  "code-line-height": {
    "value": "{line-height-200}",
    "component": "code"
  },
  "code-line-height-cjk": {
    "value": "{line-height-cjk-200}",
    "component": "code"
  }
}
